xpm/__init__.py
xpm/commandmanager.py
xpm/installmanager.py
xpm/pathmanager.py
xpm/projectmanager.py
xpm/templatemanager.py
xpm/directorystructure/__init__.py
xpm/directorystructure/installerprojectdirectorystructure.py
xpm/directorystructure/projectdirectorystructure.py
xpm/package/__init__.py
xpm/package/packagedata.py
xpm/package/packagemanager.py
xpm/script/__init__.py
xpm/script/basescriptmanager.py
xpm/script/bashscriptmanager.py
xpm/script/batchscriptmanager.py
xpm/script/pipeline.py
xpm/script/scriptfunctiontype.py
xpm/script/scripttype.py
xpm/test/__init__.py
xpm/test/testclass.py
xpm/test/testmanager.py
xpm/version/__init__.py
xpm/version/incrementalversiondata.py
xpm/version/semanticversiondata.py
xpm/version/versiondata.py
xpm/version/versionmanager.py
xid_xpm-0.0.25.dist-info/LICENSE
xid_xpm-0.0.25.dist-info/METADATA
xid_xpm-0.0.25.dist-info/WHEEL
xid_xpm-0.0.25.dist-info/entry_points.txt
xid_xpm-0.0.25.dist-info/top_level.txt
xid_xpm-0.0.25.dist-info/RECORD
