Metadata-Version: 2.2
Name: xid-xpm
Version: 0.0.25
Summary: Xidware Python project Manager
Home-page: https://xidware.com
Author: xidware
Author-email: developer@xidware.com
Classifier: Programming Language :: Python :: 3
Classifier: License :: OSI Approved :: MIT License
Classifier: Operating System :: OS Independent
Requires-Python: >=3.9.7
License-File: LICENSE
Requires-Dist: xid-xpl
Dynamic: author
Dynamic: author-email
Dynamic: classifier
Dynamic: description
Dynamic: description-content-type
Dynamic: home-page
Dynamic: requires-dist
Dynamic: requires-python
Dynamic: summary
